{
  "toolId": "sentence-counter",
  "locale": "fr",
  "slug": "compteur-de-phrases",
  "h1": "Compteur de phrases",
  "title": "Compteur de phrases",
  "shortDescription": "Comptez instantanément les phrases d’un texte avec des résultats rapides, une saisie simple et des exemples pratiques.",
  "overview": "Comptez instantanément les phrases d’un texte. Cette page fournit une réponse rapide grâce à un outil pratique et à un parcours de résultat simple. Elle s’adresse aux utilisateurs qui recherchent une réponse gratuite en ligne, des résultats immédiats dans le navigateur et un contenu utilitaire pratique pour les requêtes longue traîne.",
  "howItWorks": [
    "Saisissez le texte demandé dans le formulaire.",
    "Le comptage s’effectue instantanément dans le navigateur.",
    "Consultez le résultat et poursuivez avec des outils associés si vous avez besoin d’une autre étape."
  ],
  "examples": [
    {
      "title": "Exemple 1",
      "input": "Un paragraphe avec plusieurs phrases.",
      "output": "Nombre total de phrases",
      "description": "Un exemple réaliste de compteur de phrases pour une requête courante."
    },
    {
      "title": "Exemple 2",
      "input": "Un paragraphe avec plusieurs phrases.",
      "output": "Nombre total de phrases",
      "description": "Un autre cas d’usage pratique pour le trafic organique longue traîne."
    }
  ],
  "faq": [
    {
      "question": "Quelle est la précision de cet outil ?",
      "answer": "Le résultat est calculé directement à partir de la logique utilisée par cet outil ou dans le navigateur."
    },
    {
      "question": "Puis-je utiliser cet outil sur mobile ?",
      "answer": "Oui. La page fonctionne sur ordinateur et mobile avec une interface simple de saisie et de résultat."
    }
  ],
  "seo": {
    "title": "Compteur de phrases",
    "description": "Comptez instantanément les phrases d’un texte. Compteur de phrases en ligne gratuit avec résultat immédiat.",
    "keywords": [
      "compteur de phrases",
      "outil de texte"
    ]
  }
}
